{
  "id": "54616ce0-a92d-4b93-8165-72dd2d748f06",
  "prevId": "00000000-0000-0000-0000-000000000000",
  "version": "7",
  "dialect": "postgresql",
  "tables": {
    "public.cardholder": {
      "name": "cardholder",
      "schema": "",
      "columns": {
        "user_id": {
          "name": "user_id",
          "type": "serial",
          "primaryKey": true,
          "notNull": true
        },
        "full_name": {
          "name": "full_name",
          "type": "varchar",
          "primaryKey": false,
          "notNull": true
        },
        "cardNumbers": {
          "name": "cardNumbers",
          "type": "integer",
          "primaryKey": false,
          "notNull": true
        },
        "month": {
          "name": "month",
          "type": "integer",
          "primaryKey": false,
          "notNull": true
        },
        "Year": {
          "name": "Year",
          "type": "integer",
          "primaryKey": false,
          "notNull": true
        },
        "CVV": {
          "name": "CVV",
          "type": "integer",
          "primaryKey": false,
          "notNull": true
        }
      },
      "indexes": {},
      "foreignKeys": {},
      "compositePrimaryKeys": {},
      "uniqueConstraints": {}
    }
  },
  "enums": {},
  "schemas": {},
  "_meta": {
    "columns": {},
    "schemas": {},
    "tables": {}
  }
}